nfsepmsj/__init__.py
nfsepmsj/client.py
nfsepmsj/utils.py
nfsepmsj/xml.py
nfsepmsj/xsd/abrasf/2.02/nfse_v202.xsd
nfsepmsj/xsd/abrasf/2.02/xmldsig-core-schema20020212.xsd
nfsepmsj/xsd/betha/01/nfse-acbr.xsd
nfsepmsj/xsd/betha/01/nfse_v01.xsd
nfsepmsj/xsd/betha/01/xmldsig-core-schema.xsd
nfsepmsj/xsd/betha/01/xmldsig-core-schema_v01.xsd
nfsepmsj-0.0.4.dist-info/LICENSE
nfsepmsj-0.0.4.dist-info/METADATA
nfsepmsj-0.0.4.dist-info/WHEEL
nfsepmsj-0.0.4.dist-info/top_level.txt
nfsepmsj-0.0.4.dist-info/RECORD
