Metadata-Version: 2.1
Name: nfsepmsj
Version: 0.0.4
Summary: Biblioteca para acesso ao Webservices de NFSe da Prefeitura Municipal de Sao Jose - SC
Home-page: https://github.com/qualitaocupacional/nfsepmsj
Author: Qualita Seguranca e Saude Ocupacional
Author-email: lab.ti@qualitaocupacional.com.br
License: Apache 2.0
Platform: UNKNOWN
Classifier: Development Status :: 3 - Alpha
Classifier: Intended Audience :: Developers
Classifier: License :: OSI Approved :: Apache Software License
Classifier: Programming Language :: Python :: 2.7
Classifier: Programming Language :: Python :: 3
Classifier: Programming Language :: Python :: 3.4
Classifier: Programming Language :: Python :: 3.5
Requires-Dist: requests (>=2.7.0)
Requires-Dist: lxml (>=4.2.1)
Requires-Dist: zeep (>=2.5.0)
Requires-Dist: signxml (>=2.5.2)
Requires-Dist: pyOpenSSL (>=17.5.0)
Requires-Dist: six (>=1.11.0)
Requires-Dist: xmltodict (>=0.12.0)
